mcp_cube_server/__init__.py
mcp_cube_server/server.py
mseep_mcp_cube_server-0.0.6.dist-info/METADATA
mseep_mcp_cube_server-0.0.6.dist-info/WHEEL
mseep_mcp_cube_server-0.0.6.dist-info/entry_points.txt
mseep_mcp_cube_server-0.0.6.dist-info/licenses/LICENSE
mseep_mcp_cube_server-0.0.6.dist-info/RECORD
