Metadata-Version: 2.4
Name: mseep-mcp_cube_server
Version: 0.0.6
Summary: MCP server for interfacing with Cube.dev REST API
Author-email: mseep <support@skydeck.ai>
License-File: LICENSE
Requires-Python: >=3.11
Requires-Dist: mcp>=1.2.1
Requires-Dist: pandas
Requires-Dist: pyjwt>=2.10.1
Requires-Dist: python-dotenv
Requires-Dist: pyyaml>=6.0.2
Requires-Dist: requests>=2.32.3
